[
	{
		"_id": "CR1",
		"image_url": "https://images.unsplash.com/photo-1648142119324-fbab91e76c66?ixlib=rb-1.2.1&ixid=MnwxMjA3fDB8MHxwaG90by1wYWdlfHx8fGVufDB8fHx8&auto=format&fit=crop&w=1174&q=80",
		"recipe_name": "Aeropress Championship 2022 Winner Recipe",
		"description": "The best coffee recipe that won the Aeropress Championship 2022",
		"average_rating": 5,
		"user": {
			"username": "john_smith",
			"email": "john_smith@gmail.com"
		},
		"date": "01-01-2010",
		"total_brew_time": "10 minutes",
		"brew_yield": "90 ml",
    "brewing_method": "BM1",
		"coffee_beans": ["C1", "C2"],
		"coffee_rest_period": "1-3 days",
		"amount_of_coffee": 36,
		"grinder": "G1",
		"grind_setting": "3 clicks",
		"water": {
			"type": "filtered",
			"amount": 250,
			"temperature": 96
		},
		"additional_ingredients": [
			{
				"ingredient_name": "milk",
				"amount": "50 ml"
			},
			{
				"ingredient_name": "mint leaf",
				"amount": "2 leaves"
			}
		],
    "brewer": "B1",
		"additional_equipment": ["wooden stirrer", "Aeropress filter paper"],
		"steps": [
			"Step 1: Grind coffee and pre-heat carafe",
			"Step 2: Add hot water to Aeropress and wait 10 minutes",
			"Step 3: Pour coffee into carafe and enjoy hot or with ice"
		],
		"reviews": [
      {
        "username": "jane_austin",
        "date": "02-02-2010",
        "title": "Best coffee recipe I've ever tried!",
        "content": "This recipe really brings out the sweetness of the coffee beans!", 
        "rating": 5
      }
    ]
	},
	{
		"_id": "CR2",
		"image_url": "https://images.unsplash.com/photo-1509042239860-f550ce710b93?ixlib=rb-1.2.1&ixid=MnwxMjA3fDB8MHxzZWFyY2h8Mnx8Y29mZmVlfGVufDB8fDB8fA%3D%3D&auto=format&fit=crop&w=500&q=60",
		"recipe_name": "Lungo",
		"description": "Simple lungo using Wacaco Picopresso",
		"average_rating": 4,
		"user": {
			"username": "jane_austin",
			"email": "jane_austin@gmail.com"
		},
		"date": "02-02-2010",
		"total_brew_time": "5 minutes",
		"brew_yield": "60 ml",
    "brewing_method": "BM2",
		"coffee_beans": ["C3"],
		"coffee_rest_period": "14+ days",
		"amount_of_coffee": 18,
		"grinder": "G2",
		"grind_setting": "9 clicks",
		"water": {
			"type": "filtered",
			"amount": 200,
			"temperature": 100
		},
		"additional_ingredients": [
			{
				"ingredient_name": "milk",
				"amount": "150 ml"
			}
		],
    "brewer": "B2",
		"additional_equipment": [],
		"steps": [
			"Step 1: Grind coffee and pre-heat brewer",
			"Step 2: Add hot water to brewer and wait 10 seconds",
			"Step 3: Extract espresso into a cup and add milk"
		],
		"reviews": [
      {
        "username": "john_smith",
        "date": "03-02-2010",
        "title": "Simple and delicious!",
        "content": "This recipe is so simple that I can do it every morning", 
        "rating": 4
      }
    ]
	},
	{
		"_id": "CR3",
		"image_url": "https://images.unsplash.com/photo-1512568400610-62da28bc8a13?ixlib=rb-1.2.1&ixid=MnwxMjA3fDB8MHxzZWFyY2h8OXx8Y29mZmVlfGVufDB8fDB8fA%3D%3D&auto=format&fit=crop&w=500&q=60",
		"recipe_name": "Simple Iced Latte",
		"description": "Inspired by Starbucks coffee",
		"average_rating": 4.5,
		"user": {
			"username": "sally_doe",
			"email": "sally_doe@gmail.com"
		},
		"date": "03-03-2010",
		"total_brew_time": "5 minutes",
		"brew_yield": "45 ml",
    "brewing_method": "BM3",
		"coffee_beans": ["C4" ],
		"coffee_rest_period": "5-7 days",
		"amount_of_coffee": 20,
		"grinder": "G3",
		"grind_setting": "5",
		"water": {
			"type": "distilled",
			"amount": 100,
			"temperature": 96
		},
		"additional_ingredients": [
			{
				"ingredient_name": "milk",
				"amount": "150 ml"
			}
		],
    "brewer": "B3",
		"additional_equipment": [],
		"steps": [
			"Step 1: Grind coffee and add to brewer",
			"Step 2: Add hot water to brewer and wait 30 seconds",
			"Step 3: Extract coffee and add cold milk"
		],
		"reviews": [
      {
        "username": "jane_austin",
        "date": "03-03-2010",
        "title": "Good!",
        "content": "This recipe really brings out the sweetness of the coffee beans!", 
        "rating": 5
      },
      {
        "username": "john_smith",
        "date": "03-03-2010",
        "title": "Amazing!",
        "content": "This recipe really brings out the sweetness of the coffee beans!", 
        "rating": 4
      }
    ]
	}
]
